deutschland/hilfsmittel/__init__.py
deutschland/hilfsmittel/api/__init__.py
deutschland/hilfsmittel/api/default_api.py
deutschland/hilfsmittel/api_client.py
deutschland/hilfsmittel/apis/__init__.py
deutschland/hilfsmittel/configuration.py
deutschland/hilfsmittel/exceptions.py
deutschland/hilfsmittel/model/__init__.py
deutschland/hilfsmittel/model/baum_knoten.py
deutschland/hilfsmittel/model/detail_produkt.py
deutschland/hilfsmittel/model/detail_produkt_all_of.py
deutschland/hilfsmittel/model/detail_produkt_all_of_kontruktionsmerkmale.py
deutschland/hilfsmittel/model/nachweisschema.py
deutschland/hilfsmittel/model/nachweisschema_nachweis_abschnitt_anforderungen_inner.py
deutschland/hilfsmittel/model/nachweisschema_nachweis_abschnitt_anforderungen_inner_abschnitt_anforderungen_inner.py
deutschland/hilfsmittel/model/nachweisschema_nachweisschema_kategorie_zuweisungen_inner.py
deutschland/hilfsmittel/model/produkt.py
deutschland/hilfsmittel/model/produktart.py
deutschland/hilfsmittel/model/produktgruppe.py
deutschland/hilfsmittel/model/untergruppe.py
deutschland/hilfsmittel/model_utils.py
deutschland/hilfsmittel/models/__init__.py
deutschland/hilfsmittel/rest.py
de_hilfsmittel-1.0.0.dist-info/WHEEL
de_hilfsmittel-1.0.0.dist-info/METADATA
de_hilfsmittel-1.0.0.dist-info/RECORD
